eventbus/__init__.py
eventbus/application/__init__.py
eventbus/application/eventbus.py
eventbus/domain/__init__.py
eventbus/domain/aggregate.py
eventbus/domain/decorators.py
eventbus/domain/entity.py
eventbus/domain/eventbus.py
eventbus/domain/events.py
eventbus/domain/exceptions.py
eventbus/domain/whitehead.py
eventbus/example/__init__.py
eventbus/example/entity.py
eventbus/util/__init__.py
eventbus/util/hashing.py
eventbus/util/topic.py
eventbus/util/transcoding.py
domain_eventbus-0.1.20.dist-info/AUTHORS.rst
domain_eventbus-0.1.20.dist-info/LICENSE
domain_eventbus-0.1.20.dist-info/METADATA
domain_eventbus-0.1.20.dist-info/WHEEL
domain_eventbus-0.1.20.dist-info/top_level.txt
domain_eventbus-0.1.20.dist-info/RECORD
